sake/__init__.py
sake/_internal.py
sake/_redis_iterators.py
sake/_tanjun_adapter.py
sake/abc.py
sake/errors.py
sake/py.typed
sake/redis.py
hikari_sake-1.1.2.dist-info/LICENSE
hikari_sake-1.1.2.dist-info/WHEEL
hikari_sake-1.1.2.dist-info/METADATA
hikari_sake-1.1.2.dist-info/RECORD
