Metadata-Version: 2.3
Name: hikari-sake
Version: 1.1.2
Summary: A distributed asynchronous cache standard designed for Hikari.
Keywords: hikari
Author-email: Faster Speeding <lucina@lmbyrne.dev>
Requires-Python: >=3.9.0,<3.14
Classifier: Development Status :: 5 - Production/Stable
Classifier: License :: OSI Approved :: BSD License
Classifier: Intended Audience :: Developers
Classifier: Natural Language :: English
Classifier: Operating System :: OS Independent
Classifier: Programming Language :: Python :: 3.9
Classifier: Programming Language :: Python :: 3.10
Classifier: Programming Language :: Python :: 3.11
Classifier: Programming Language :: Python :: 3.12
Classifier: Programming Language :: Python :: 3.13
Classifier: Programming Language :: Python :: Implementation :: CPython
Classifier: Topic :: Software Development :: Libraries
Classifier: Topic :: Software Development :: Libraries :: Python Modules
Classifier: Topic :: Utilities
Classifier: Typing :: Typed
Requires-Dist: hikari>=2.0.0.dev112, <3
Requires-Dist: redis~=4.2
Requires-Dist: hikari-tanjun>=2.9.0a1, <3 ; extra == "tanjun"
Project-URL: Changelog, https://sake.cursed.solutions/changelog
Project-URL: Documentation, https://sake.cursed.solutions
Project-URL: Homepage, https://github.com/FasterSpeeding/Sake
Project-URL: Repository, https://github.com/FasterSpeeding/Sake
Provides-Extra: tanjun
